biogram/__init__.py
biogram/_sqlalchemy.py
biogram/_utils.py
biogram-0.0.2.dist-info/LICENSE
biogram-0.0.2.dist-info/WHEEL
biogram-0.0.2.dist-info/METADATA
biogram-0.0.2.dist-info/RECORD
