Metadata-Version: 2.1
Name: biogram
Version: 0.0.2
Summary: Make diagrams for biological entities.
Author-email: Lamin Labs <laminlabs@gmail.com>
Requires-Dist: nbproject
Requires-Dist: pydot
Requires-Dist: sqlalchemy
Requires-Dist: pre-commit ; extra == "dev"
Requires-Dist: nox ; extra == "dev"
Requires-Dist: pytest>=6.0 ; extra == "test"
Requires-Dist: nbmake ; extra == "test"
Project-URL: Home, https://github.com/laminlabs/biogram
Provides-Extra: dev
Provides-Extra: test
